ToonBoom/__init__.py
ToonBoom/harmony.py
fake_harmony_module-0.0.2.dist-info/LICENSE
fake_harmony_module-0.0.2.dist-info/METADATA
fake_harmony_module-0.0.2.dist-info/WHEEL
fake_harmony_module-0.0.2.dist-info/top_level.txt
fake_harmony_module-0.0.2.dist-info/RECORD
