Metadata-Version: 2.1
Name: fake-harmony-module
Version: 0.0.2
Summary: Fake harmony module
Author: Tristan Languebien
Author-email: <tlanguebien@gmail.com>
Keywords: python,toonboom,harmony
Classifier: Development Status :: 1 - Planning
Classifier: Intended Audience :: Developers
Classifier: Programming Language :: Python :: 3
Classifier: Operating System :: Unix
Classifier: Operating System :: MacOS :: MacOS X
Classifier: Operating System :: Microsoft :: Windows
License-File: LICENSE
